spantools/__init__.py
spantools/_content_dump.py
spantools/_content_load.py
spantools/_encoders.py
spantools/_errors.py
spantools/_mimetype.py
spantools/_models.py
spantools/_typing.py
spantools/_utils.py
spantools/_version.py
spantools/errors_api/__init__.py
spantools/errors_api/_classes.py
spantools-0.2.3.dist-info/LICENSE
spantools-0.2.3.dist-info/METADATA
spantools-0.2.3.dist-info/WHEEL
spantools-0.2.3.dist-info/top_level.txt
spantools-0.2.3.dist-info/RECORD
